[
    {
        "policy": {
            "version": "2012-10-17", 
            "Statement": [
                {
                    "Action": [
                        "ec2:DescribeVolumes"
                    ], 
                    "Resource": [
                        "*"
                    ], 
                    "Effect": "Allow", 
                    "Sid": "statement1"
                }
            ]
        }, 
        "request": "DescribeVolumesRequest(Filters=[Filter()])", 
        "apiName": "ec2.describeVolumes"
    }, 
    {
        "policy": {
            "version": "2012-10-17", 
            "Statement": [
                {
                    "Action": [
                        "ec2:DescribeVolumes"
                    ], 
                    "Resource": [
                        "*"
                    ], 
                    "Effect": "Allow", 
                    "Sid": "statement1"
                }
            ]
        }, 
        "request": "DescribeVolumesRequest(Filters=[Filter()], MaxResults=100)", 
        "apiName": "ec2.describeVolumes"
    }, 
    {
        "policy": {
            "version": "2012-10-17", 
            "Statement": [
                {
                    "Action": [
                        "ec2:DescribeVolumes"
                    ], 
                    "Resource": [
                        "*"
                    ], 
                    "Effect": "Allow", 
                    "Sid": "statement1"
                }
            ]
        }, 
        "request": "DescribeVolumesRequest(Filters=[Filter()], NextToken=)", 
        "apiName": "ec2.describeVolumes"
    }, 
    {
        "policy": {
            "version": "2012-10-17", 
            "Statement": [
                {
                    "Action": [
                        "ec2:DescribeVolumes"
                    ], 
                    "Resource": [
                        "*"
                    ], 
                    "Effect": "Allow", 
                    "Sid": "statement1"
                }
            ]
        }, 
        "request": "DescribeVolumesRequest(Filters=[Filter()], MaxResults=100, NextToken=)", 
        "apiName": "ec2.describeVolumes"
    }, 
    {
        "policy": {
            "version": "2012-10-17", 
            "Statement": [
                {
                    "Action": [
                        "ec2:DescribeVolumes"
                    ], 
                    "Resource": [
                        "*"
                    ], 
                    "Effect": "Allow", 
                    "Sid": "statement1"
                }
            ]
        }, 
        "request": "DescribeVolumesRequest(Filters=[Filter()], NextToken=)", 
        "apiName": "ec2.describeVolumes"
    }, 
    {
        "policy": {
            "version": "2012-10-17", 
            "Statement": [
                {
                    "Action": [
                        "ec2:DescribeVolumes"
                    ], 
                    "Resource": [
                        "*"
                    ], 
                    "Effect": "Allow", 
                    "Sid": "statement1"
                }
            ]
        }, 
        "request": "DescribeVolumesRequest(Filters=[Filter()], MaxResults=100, NextToken=)", 
        "apiName": "ec2.describeVolumes"
    }
]