[
    {
        "policy": {
            "version": "2012-10-17", 
            "Statement": [
                {
                    "Action": [
                        "s3:GetBucketWebsite"
                    ], 
                    "Resource": [
                        "arn:aws:s3:::test-bucket-5461"
                    ], 
                    "Effect": "Allow", 
                    "Sid": "statement1"
                }
            ]
        }, 
        "request": "GetBucketWebsiteRequest(Bucket=test-bucket-5461, ExpectedBucketOwner=002677082836)", 
        "apiName": "getBucketWebsite"
    }, 
    {
        "policy": {
            "version": "2012-10-17", 
            "Statement": [
                {
                    "Action": [
                        "s3:GetBucketWebsite"
                    ], 
                    "Resource": [
                        "arn:aws:s3:::test-bucket-5461"
                    ], 
                    "Effect": "Allow", 
                    "Sid": "statement1"
                }
            ]
        }, 
        "request": "GetBucketWebsiteRequest(Bucket=test-bucket-5461)", 
        "apiName": "getBucketWebsite"
    }, 
    {
        "policy": {
            "version": "2012-10-17", 
            "Statement": [
                {
                    "Action": [
                        "s3:GetBucketWebsite"
                    ], 
                    "Resource": [
                        "arn:aws:s3:::test-bucket-5461"
                    ], 
                    "Effect": "Allow", 
                    "Sid": "statement1"
                }
            ]
        }, 
        "request": "GetBucketWebsiteRequest(Bucket=test-bucket-5461)", 
        "apiName": "getBucketWebsite"
    }, 
    {
        "policy": {
            "version": "2012-10-17", 
            "Statement": [
                {
                    "Action": [
                        "s3:GetBucketWebsite"
                    ], 
                    "Resource": [
                        "arn:aws:s3:::test-bucket-5461"
                    ], 
                    "Effect": "Allow", 
                    "Sid": "statement1"
                }
            ]
        }, 
        "request": "GetBucketWebsiteRequest(Bucket=test-bucket-5461, ExpectedBucketOwner=002677082836)", 
        "apiName": "getBucketWebsite"
    }
]