[
    {
        "policy": {
            "version": "2012-10-17", 
            "Statement": [
                {
                    "Action": [
                        "s3:PutMetricsConfiguration"
                    ], 
                    "Resource": [
                        "arn:aws:s3:::test-bucket-5461"
                    ], 
                    "Effect": "Allow", 
                    "Sid": "statement1"
                }
            ]
        }, 
        "request": "PutBucketMetricsConfigurationRequest(Bucket=test-bucket-5461, Id=test-bucket-5461-metrics, MetricsConfiguration=MetricsConfiguration(Id=test-bucket-5461-metrics, Filter=MetricsFilter(Prefix=test-bucket-5461)))", 
        "apiName": "s3.putBucketMetricsConfiguration"
    }
]